[
  {
    "description": "",
    "name": "xxl",
    "verified_type": "none",
    "public_metrics": {
      "followers_count": 509,
      "following_count": 1307,
      "tweet_count": 8254,
      "listed_count": 9,
      "like_count": 1492,
      "media_count": 2338
    },
    "id": "4714948245",
    "created_at": "2016-01-05T13:18:58.000Z",
    "username": "Michael55586731"
  },
  {
    "description": "Columnist for Byline Times. Host of 'The CJ Werleman Show' on YouTube. Activist against Islamophobia. Plz support: https://t.co/pfRnwbDSl0",
    "name": "CJ Werleman",
    "verified_type": "blue",
    "withheld": {
      "country_codes": [
        "IN"
      ]
    },
    "public_metrics": {
      "followers_count": 385222,
      "following_count": 4487,
      "tweet_count": 83398,
      "listed_count": 2741,
      "like_count": 137985,
      "media_count": 10235
    },
    "id": "33519870",
    "created_at": "2009-04-20T13:59:10.000Z",
    "username": "cjwerleman"
  },
  {
    "description": "News To Expand Your Views",
    "name": "HawkFeed",
    "verified_type": "none",
    "public_metrics": {
      "followers_count": 167,
      "following_count": 5,
      "tweet_count": 125,
      "listed_count": 2,
      "like_count": 5,
      "media_count": 0
    },
    "id": "4355853074",
    "created_at": "2015-11-25T12:40:54.000Z",
    "username": "HawkFeed"
  },
  {
    "description": "Disability self-advocate, PTA mom, political strategist, Minnesotan(ish), collector of cats. | I cry a lot but I am so productive. It\u2019s an art (TS). she/her",
    "name": "I would prefer not to",
    "verified_type": "none",
    "public_metrics": {
      "followers_count": 4469,
      "following_count": 4405,
      "tweet_count": 53380,
      "listed_count": 63,
      "like_count": 67849,
      "media_count": 1027
    },
    "id": "14342665",
    "created_at": "2008-04-09T15:40:18.000Z",
    "username": "thequeengeek"
  },
  {
    "description": "@crookedmedia co-founder, podcast host, former presidential speechwriter. Mostly water.",
    "name": "Jon Lovett",
    "verified_type": "blue",
    "public_metrics": {
      "followers_count": 733593,
      "following_count": 1895,
      "tweet_count": 3674,
      "listed_count": 6265,
      "like_count": 5220,
      "media_count": 264
    },
    "id": "174110843",
    "created_at": "2010-08-03T03:41:01.000Z",
    "username": "jonlovett"
  },
  {
    "description": "Founder of research firm - AlphaTarget. Previously,  Founder / Portfolio manager of money management firms in Hong Kong. \n\nNo investment advice, do your own DD.",
    "name": "Puru Saxena",
    "verified_type": "blue",
    "public_metrics": {
      "followers_count": 376636,
      "following_count": 125,
      "tweet_count": 50796,
      "listed_count": 7018,
      "like_count": 123504,
      "media_count": 3985
    },
    "id": "1033127171298975744",
    "created_at": "2018-08-24T23:01:27.000Z",
    "username": "saxena_puru"
  },
  {
    "description": "Talent Manager\nCEO at ABA MGT AGENCY\n Talent Manager at SoundPrints #MK26",
    "name": "A B A \ud83c\uddfa\ud83c\uddec Rasta",
    "verified_type": "none",
    "public_metrics": {
      "followers_count": 2079,
      "following_count": 2027,
      "tweet_count": 6729,
      "listed_count": 1,
      "like_count": 14289,
      "media_count": 540
    },
    "id": "865212096983781378",
    "created_at": "2017-05-18T14:26:53.000Z",
    "username": "Aba_Xtreme"
  },
  {
    "description": "Chancellor of @SUNY, the largest comprehensive system of higher education in America. Committed to equity and opportunity for all. Follow @JohnBKing for more.",
    "name": "Chancellor John B. King",
    "verified_type": "blue",
    "public_metrics": {
      "followers_count": 1897,
      "following_count": 584,
      "tweet_count": 1497,
      "listed_count": 10,
      "like_count": 1476,
      "media_count": 914
    },
    "id": "1481259498341810177",
    "created_at": "2022-01-12T13:39:47.000Z",
    "username": "SUNYChancellor"
  },
  {
    "description": "Looking for original cosmetics from top brands? We've got your back. Follow us for original makeup and cosmetic products from top brands at affordable prices.",
    "name": "Original Cosmetics",
    "verified_type": "none",
    "public_metrics": {
      "followers_count": 695,
      "following_count": 120,
      "tweet_count": 4078,
      "listed_count": 4,
      "like_count": 683,
      "media_count": 1218
    },
    "id": "719884795459858432",
    "created_at": "2016-04-12T13:48:04.000Z",
    "username": "cosmeticsng"
  },
  {
    "description": "Can you hear us now?",
    "name": "Verizon",
    "verified_type": "business",
    "public_metrics": {
      "followers_count": 1537879,
      "following_count": 142,
      "tweet_count": 36815,
      "listed_count": 5249,
      "like_count": 24673,
      "media_count": 3290
    },
    "id": "59889953",
    "created_at": "2009-07-24T21:13:55.000Z",
    "username": "Verizon"
  },
  {
    "description": "Ugly building lover, Business owner, Dad x4, Husband x1, Former Army Guy",
    "name": "Brandon Wurz",
    "verified_type": "blue",
    "public_metrics": {
      "followers_count": 10236,
      "following_count": 1434,
      "tweet_count": 24736,
      "listed_count": 229,
      "like_count": 23576,
      "media_count": 3017
    },
    "id": "1417629775",
    "created_at": "2013-05-10T09:12:03.000Z",
    "username": "excel_ranger"
  },
  {
    "description": "Black, Puerto Rican and Filipino. Proud to be a Person of Color and a Non-Victim. \nI worked hard for everything I have and nobody got in my way.",
    "name": "Ex-Democrat and now UltraMAGAaf",
    "verified_type": "none",
    "public_metrics": {
      "followers_count": 108,
      "following_count": 255,
      "tweet_count": 2525,
      "listed_count": 0,
      "like_count": 204,
      "media_count": 76
    },
    "id": "38729412",
    "created_at": "2009-05-08T19:43:40.000Z",
    "username": "keviemac"
  },
  {
    "description": "OFFICIAL Twitter page of Dick Morris. Visit https://t.co/r25mxVhjmL for Dick's Political commentary!",
    "name": "Dick Morris",
    "verified_type": "blue",
    "public_metrics": {
      "followers_count": 185770,
      "following_count": 256,
      "tweet_count": 11506,
      "listed_count": 2504,
      "like_count": 87,
      "media_count": 52
    },
    "id": "49140008",
    "created_at": "2009-06-20T22:22:04.000Z",
    "username": "DickMorrisTweet"
  },
  {
    "description": "A higher degree of healthcare in Washington state. Connecting patient care with a top-rated medical school and a research powerhouse.",
    "name": "UW Medicine",
    "verified_type": "none",
    "public_metrics": {
      "followers_count": 35565,
      "following_count": 1309,
      "tweet_count": 21224,
      "listed_count": 705,
      "like_count": 10913,
      "media_count": 2637
    },
    "id": "36784717",
    "created_at": "2009-04-30T21:55:05.000Z",
    "username": "UWMedicine"
  },
  {
    "description": "Video Games, Comic Books, Space, and Technology fan. Computer Information Systems Major http://t.co/POkc0FWHfK",
    "name": "Spencer",
    "verified_type": "none",
    "public_metrics": {
      "followers_count": 114,
      "following_count": 0,
      "tweet_count": 17858,
      "listed_count": 13,
      "like_count": 4319,
      "media_count": 1334
    },
    "id": "186083685",
    "created_at": "2010-09-02T15:01:54.000Z",
    "username": "TheGeekIntel"
  },
  {
    "description": "\u2764\ufe0f\ud83e\udddf\u200d\u2642\ufe0f Dating a Nightmare: Avoiding, Surviving and Escaping a Covert Narcissist \u2757\ufe0fOut Now\u2757\ufe0f{link in bio}",
    "name": "Narcissistic Support",
    "verified_type": "blue",
    "public_metrics": {
      "followers_count": 11661,
      "following_count": 1861,
      "tweet_count": 3767,
      "listed_count": 65,
      "like_count": 3608,
      "media_count": 642
    },
    "id": "4905436810",
    "created_at": "2016-02-13T17:15:41.000Z",
    "username": "narcsupport101"
  },
  {
    "description": "Father of Sam & Charlie, husband to Renee.  Former candidate for the U.S. Senate.",
    "name": "Luke Mixon",
    "verified_type": "none",
    "public_metrics": {
      "followers_count": 62514,
      "following_count": 185,
      "tweet_count": 2288,
      "listed_count": 125,
      "like_count": 363,
      "media_count": 561
    },
    "id": "1441111022283079682",
    "created_at": "2021-09-23T18:44:05.000Z",
    "username": "LukeMixonLA"
  },
  {
    "description": "The official account of #GhostAdventures. \ud83d\udc7b",
    "name": "Ghost Adventures",
    "verified_type": "blue",
    "public_metrics": {
      "followers_count": 1022910,
      "following_count": 1976,
      "tweet_count": 10269,
      "listed_count": 2902,
      "like_count": 2383,
      "media_count": 1403
    },
    "id": "17454419",
    "created_at": "2008-11-18T00:23:48.000Z",
    "username": "GhostAdventures"
  },
  {
    "description": "Mostly sunny. Opinions are mine.",
    "name": "Janice Dean",
    "verified_type": "blue",
    "public_metrics": {
      "followers_count": 627562,
      "following_count": 10511,
      "tweet_count": 79941,
      "listed_count": 1266,
      "like_count": 100351,
      "media_count": 9688
    },
    "id": "111400999",
    "created_at": "2010-02-04T20:07:06.000Z",
    "username": "JaniceDean"
  },
  {
    "description": "Love God, family and country",
    "name": "Blessed",
    "verified_type": "blue",
    "public_metrics": {
      "followers_count": 67,
      "following_count": 813,
      "tweet_count": 717,
      "listed_count": 2,
      "like_count": 2016,
      "media_count": 18
    },
    "id": "561842610",
    "created_at": "2012-04-24T05:48:13.000Z",
    "username": "lotsoblessings"
  },
  {
    "description": "Democracy Dies in Darkness",
    "name": "The Washington Post",
    "verified_type": "business",
    "public_metrics": {
      "followers_count": 19833087,
      "following_count": 1640,
      "tweet_count": 517132,
      "listed_count": 104558,
      "like_count": 3768,
      "media_count": 21531
    },
    "id": "2467791",
    "created_at": "2007-03-27T11:19:39.000Z",
    "username": "washingtonpost"
  },
  {
    "description": "A website for Habs fans, by Habs fans | En Fran\u00e7ais aussi!",
    "name": "Rabid Habs",
    "verified_type": "none",
    "public_metrics": {
      "followers_count": 5315,
      "following_count": 2200,
      "tweet_count": 21649,
      "listed_count": 90,
      "like_count": 3648,
      "media_count": 1844
    },
    "id": "491870816",
    "created_at": "2012-02-14T03:24:21.000Z",
    "username": "rabidhabs"
  },
  {
    "description": "",
    "name": "offinrunnin88",
    "verified_type": "none",
    "public_metrics": {
      "followers_count": 34,
      "following_count": 115,
      "tweet_count": 4,
      "listed_count": 0,
      "like_count": 60,
      "media_count": 0
    },
    "id": "202228991",
    "created_at": "2010-10-13T15:46:02.000Z",
    "username": "offinrunnin88"
  },
  {
    "description": "Congressman for Colorado\u2019s 2nd District \u26f0\ufe0f| Andrea\u2019s husband | Dad to 2 wonderful kids | Attorney | Fmr State Cabinet Member & CU Regent | Denver Nuggets Fan \ud83c\udfc0",
    "name": "Joe Neguse",
    "verified_type": "government",
    "public_metrics": {
      "followers_count": 67969,
      "following_count": 1015,
      "tweet_count": 2901,
      "listed_count": 559,
      "like_count": 6060,
      "media_count": 649
    },
    "id": "1542372750",
    "created_at": "2013-06-24T03:30:41.000Z",
    "username": "JoeNeguse"
  },
  {
    "description": "",
    "name": "GalaxyProtocol",
    "verified_type": "none",
    "public_metrics": {
      "followers_count": 195,
      "following_count": 0,
      "tweet_count": 0,
      "listed_count": 0,
      "like_count": 0,
      "media_count": 0
    },
    "id": "1406351372832890882",
    "created_at": "2021-06-19T20:41:24.000Z",
    "username": "SafeGalaxyToken"
  },
  {
    "description": "Brooklyn, NY. Self Taught Artist/Curator/Art Director. Marketing and Entrepreneurial Strategies.   Email:  secretstickerclub@gmail.com",
    "name": "COSBE",
    "verified_type": "none",
    "public_metrics": {
      "followers_count": 485,
      "following_count": 1695,
      "tweet_count": 20716,
      "listed_count": 15,
      "like_count": 40,
      "media_count": 74
    },
    "id": "776516618",
    "created_at": "2012-08-23T18:35:46.000Z",
    "username": "COSBE1"
  },
  {
    "description": "God loving Christian, Patriot, Proud to be born in the USA. Seeking the cure for liberalism\u2026because it is a mental illness. #WalkAway #PatriotParty #UltraMAGA",
    "name": "FreedomFighter",
    "verified_type": "none",
    "public_metrics": {
      "followers_count": 1392,
      "following_count": 1367,
      "tweet_count": 81423,
      "listed_count": 19,
      "like_count": 39921,
      "media_count": 16328
    },
    "id": "16208276",
    "created_at": "2008-09-09T19:20:53.000Z",
    "username": "FreedomUSA4"
  },
  {
    "description": "Life is good, Dave is fat. -139lbs so far. Aspiring supermodel. I\u2019m going to be a dad! IG https://t.co/Jf1DMnpCxu FB https://t.co/xF9GloDwdK",
    "name": "Dave Danna",
    "verified_type": "blue",
    "public_metrics": {
      "followers_count": 80621,
      "following_count": 2151,
      "tweet_count": 127836,
      "listed_count": 113,
      "like_count": 705599,
      "media_count": 9527
    },
    "id": "1221556511794769933",
    "created_at": "2020-01-26T22:12:35.000Z",
    "username": "DaveEDanna"
  },
  {
    "description": "Follow me for Small Business Buying/Selling Info. \nCEO of Dealonomy, the new/best business deal transaction platform. \nDad, Husband, Christian, Pilot, Texan.",
    "name": "Clint Fiore \ud83e\uddac DM for Biz Deals",
    "verified_type": "blue",
    "public_metrics": {
      "followers_count": 60565,
      "following_count": 1221,
      "tweet_count": 27087,
      "listed_count": 675,
      "like_count": 77438,
      "media_count": 2176
    },
    "id": "1477461366185287682",
    "created_at": "2022-01-02T02:08:35.000Z",
    "username": "ClintFiore"
  },
  {
    "description": "Big Data. Behavioral Microtargeting. Political Campaign Support. Digital Support.",
    "name": "Cambridge Analytica",
    "verified_type": "none",
    "public_metrics": {
      "followers_count": 28908,
      "following_count": 939,
      "tweet_count": 787,
      "listed_count": 392,
      "like_count": 115,
      "media_count": 103
    },
    "id": "3415205164",
    "created_at": "2015-08-11T12:40:54.000Z",
    "username": "CamAnalytica"
  },
  {
    "description": "U.S. Congress, 5th & 4th Districts of Iowa 2003-2021 Author, \u201cWalking Through The Fire\u201d \u2014 \u2018My Fight for the Heart and Soul of America\u2019 buy at https://t.co/oI98HbkiND",
    "name": "Steve King",
    "verified_type": "blue",
    "public_metrics": {
      "followers_count": 103769,
      "following_count": 460,
      "tweet_count": 5937,
      "listed_count": 1879,
      "like_count": 151,
      "media_count": 671
    },
    "id": "48117116",
    "created_at": "2009-06-17T21:09:41.000Z",
    "username": "SteveKingIA"
  },
  {
    "description": "Every animal is someone \ud83d\udc30\ud83d\udc2d\ud83d\udc37\ud83d\udc35\ud83d\udc2e\ud83d\udc36",
    "name": "PETA",
    "verified_type": "business",
    "public_metrics": {
      "followers_count": 1048409,
      "following_count": 2719,
      "tweet_count": 553049,
      "listed_count": 7296,
      "like_count": 115262,
      "media_count": 118718
    },
    "id": "9890492",
    "created_at": "2007-11-02T16:29:30.000Z",
    "username": "peta"
  },
  {
    "description": "The Wannabe Astronaut! \ud83d\ude80",
    "name": "Jeff",
    "verified_type": "none",
    "public_metrics": {
      "followers_count": 83,
      "following_count": 144,
      "tweet_count": 204,
      "listed_count": 1,
      "like_count": 208,
      "media_count": 37
    },
    "id": "1768263037146836992",
    "created_at": "2024-03-14T13:09:11.000Z",
    "username": "JeffGoins"
  },
  {
    "description": "Princess Di was a teacher\u2019s aide, so I became a teacher\u2019s aide.",
    "name": "Talia Bernadette\ud83c\udf19",
    "verified_type": "none",
    "public_metrics": {
      "followers_count": 444,
      "following_count": 552,
      "tweet_count": 30094,
      "listed_count": 6,
      "like_count": 38180,
      "media_count": 3506
    },
    "id": "347446013",
    "created_at": "2011-08-02T20:21:45.000Z",
    "username": "usertalia"
  },
  {
    "description": "Patriotic, irredeemably deplorable millennials who enjoy making liberals cry one tweet at a time! Email: Hispanics4Trump@gmail.com",
    "name": "Hispanics for Trump",
    "verified_type": "none",
    "public_metrics": {
      "followers_count": 76652,
      "following_count": 1535,
      "tweet_count": 4449,
      "listed_count": 148,
      "like_count": 7575,
      "media_count": 971
    },
    "id": "3837629183",
    "created_at": "2015-10-01T23:01:05.000Z",
    "username": "HispanicsTrump"
  },
  {
    "description": "Liverpool born, Brooklyn citizen. Evertonian. Financial columnist at @DowJones\u2019 @MarketWatch. @90MinsWithNev podcast co-host. Sprint triathlete.",
    "name": "James Rogers",
    "verified_type": "none",
    "public_metrics": {
      "followers_count": 9274,
      "following_count": 1858,
      "tweet_count": 13870,
      "listed_count": 208,
      "like_count": 4186,
      "media_count": 328
    },
    "id": "106779916",
    "created_at": "2010-01-20T17:31:08.000Z",
    "username": "jamesjrogers"
  },
  {
    "description": "\u00a1DeSantis 2028!",
    "name": "\ud83c\uddfa\ud83c\uddf8I Got Algorhythm \ud83c\uddfa\ud83c\uddf8",
    "verified_type": "none",
    "public_metrics": {
      "followers_count": 387,
      "following_count": 1322,
      "tweet_count": 29057,
      "listed_count": 1,
      "like_count": 2891,
      "media_count": 2373
    },
    "id": "22673229",
    "created_at": "2009-03-03T20:26:35.000Z",
    "username": "IGotAlgorhythm"
  },
  {
    "description": "\ud83c\udfa5 NOW PLAYING \u2192 @Superman\n\ud83c\udfac COMING SOON \u2192 @FantasticFour, @GratefulDead, #Jaws, and more!",
    "name": "IMAX",
    "verified_type": "business",
    "public_metrics": {
      "followers_count": 665642,
      "following_count": 803,
      "tweet_count": 35409,
      "listed_count": 2942,
      "like_count": 18786,
      "media_count": 11012
    },
    "id": "22821175",
    "created_at": "2009-03-04T19:35:10.000Z",
    "username": "IMAX"
  },
  {
    "description": "",
    "name": "Doneizzy",
    "verified_type": "none",
    "public_metrics": {
      "followers_count": 17,
      "following_count": 187,
      "tweet_count": 14,
      "listed_count": 0,
      "like_count": 195,
      "media_count": 1
    },
    "id": "1058351032613457920",
    "created_at": "2018-11-02T13:32:04.000Z",
    "username": "Doneizzy2"
  },
  {
    "description": "CNN's new home for art, fashion, architecture, design, luxury and everything that catches our eye in between.",
    "name": "CNN Style",
    "verified_type": "none",
    "public_metrics": {
      "followers_count": 36450,
      "following_count": 390,
      "tweet_count": 5726,
      "listed_count": 358,
      "like_count": 248,
      "media_count": 4558
    },
    "id": "3030352151",
    "created_at": "2015-02-11T14:00:23.000Z",
    "username": "CNNStyle"
  },
  {
    "description": "Unreconstructed crank leftie. Ex Labour....I don't want to be on any list and will block in the blink of an eye. No DMs please - unless I know you personally.",
    "name": "JuliaDoe",
    "verified_type": "none",
    "public_metrics": {
      "followers_count": 3359,
      "following_count": 3596,
      "tweet_count": 118480,
      "listed_count": 2,
      "like_count": 32897,
      "media_count": 223
    },
    "id": "2603035003",
    "created_at": "2014-07-04T07:45:07.000Z",
    "username": "Juliadoe51"
  },
  {
    "description": "The official account of the US Open Tennis Championships | #USOpen",
    "name": "US Open Tennis",
    "verified_type": "business",
    "public_metrics": {
      "followers_count": 2385739,
      "following_count": 1078,
      "tweet_count": 67035,
      "listed_count": 10849,
      "like_count": 35863,
      "media_count": 33886
    },
    "id": "14836197",
    "created_at": "2008-05-19T18:35:03.000Z",
    "username": "usopen"
  },
  {
    "description": "Journalist till I die. Now NDTV (#KhabronKiKhabar). Ex-ABP/News18India/ ZeeNews/ AajTak/ IndianExpress & Jansatta. RT r not endorsement.",
    "name": "awasthis",
    "verified_type": "blue",
    "public_metrics": {
      "followers_count": 1072678,
      "following_count": 2871,
      "tweet_count": 129593,
      "listed_count": 562,
      "like_count": 41812,
      "media_count": 7649
    },
    "id": "71815077",
    "created_at": "2009-09-05T14:42:51.000Z",
    "username": "awasthis"
  },
  {
    "description": "",
    "name": "WeTheBestMusic",
    "verified_type": "none",
    "public_metrics": {
      "followers_count": 71152,
      "following_count": 1856,
      "tweet_count": 16790,
      "listed_count": 245,
      "like_count": 221,
      "media_count": 1309
    },
    "id": "45887164",
    "created_at": "2009-06-09T17:20:23.000Z",
    "username": "WeTheBestMusic"
  },
  {
    "description": "Philosopher scientist, https://t.co/Bm8ym5R3id \u2014 New books, EXPRESSLY HUMAN and MOTORCYCLE MIND \u2014 Science Moment Podcast, YouTube \u2014 Iranian-American",
    "name": "Mark Changizi",
    "verified_type": "blue",
    "public_metrics": {
      "followers_count": 66929,
      "following_count": 912,
      "tweet_count": 172755,
      "listed_count": 777,
      "like_count": 102897,
      "media_count": 15522
    },
    "id": "49445813",
    "created_at": "2009-06-21T22:10:51.000Z",
    "username": "MarkChangizi"
  },
  {
    "description": "Sign up for our newsletters and alerts: https://t.co/QevH0DLQi8 | Got a tip? https://t.co/iXIigdPjEZ | For WSJ customer support: https://t.co/DZgH9n53qg",
    "name": "The Wall Street Journal",
    "verified_type": "business",
    "public_metrics": {
      "followers_count": 20799403,
      "following_count": 1064,
      "tweet_count": 474901,
      "listed_count": 125860,
      "like_count": 1069,
      "media_count": 51855
    },
    "id": "3108351",
    "created_at": "2007-04-01T06:22:13.000Z",
    "username": "WSJ"
  },
  {
    "description": "Cincinnati Children's, ranked one of the best children\u2019s hospitals in the nation by U.S. News & World Report",
    "name": "Cincinnati Children's",
    "verified_type": "business",
    "public_metrics": {
      "followers_count": 36272,
      "following_count": 991,
      "tweet_count": 9442,
      "listed_count": 545,
      "like_count": 1376,
      "media_count": 3392
    },
    "id": "40927068",
    "created_at": "2009-05-18T17:59:54.000Z",
    "username": "CincyChildrens"
  },
  {
    "description": "Landmark, award-winning hotel in uMmhlanga, synonymous with elegance, gracious hospitality and intuitive service since 1964.",
    "name": "Beverly Hills Hotel",
    "verified_type": "none",
    "public_metrics": {
      "followers_count": 4363,
      "following_count": 536,
      "tweet_count": 2638,
      "listed_count": 29,
      "like_count": 922,
      "media_count": 864
    },
    "id": "1353774181",
    "created_at": "2013-04-15T07:44:42.000Z",
    "username": "BevHillsZA"
  },
  {
    "description": "Journalist & editor \ud83d\udcda Writing my debut memoir about breaking my back abroad \ud83c\udf0e Find my articles on @cantravelmag, @explore_mag, @globeandmail & @fodorstravel",
    "name": "Alison Karlene Hodgins",
    "verified_type": "none",
    "public_metrics": {
      "followers_count": 1643,
      "following_count": 1402,
      "tweet_count": 3517,
      "listed_count": 121,
      "like_count": 3802,
      "media_count": 726
    },
    "id": "957398035",
    "created_at": "2012-11-19T13:02:25.000Z",
    "username": "AlisonKarlene"
  },
  {
    "description": "",
    "name": "Blair St. Clair",
    "verified_type": "none",
    "public_metrics": {
      "followers_count": 164740,
      "following_count": 371,
      "tweet_count": 7157,
      "listed_count": 425,
      "like_count": 39099,
      "media_count": 605
    },
    "id": "846962629222563843",
    "created_at": "2017-03-29T05:50:01.000Z",
    "username": "BlairStClair"
  },
  {
    "description": "\u00bfPor qu\u00e9 no te gusta la poes\u00eda? \u00bfQui\u00e9n le quit\u00f3 a tu tristeza el dolor? Poes\u00edas de Juan Romeu.",
    "name": "Poes\u00edas y l\u00e1grimas",
    "verified_type": "none",
    "public_metrics": {
      "followers_count": 11277,
      "following_count": 45,
      "tweet_count": 11357,
      "listed_count": 64,
      "like_count": 5056,
      "media_count": 2286
    },
    "id": "3133343855",
    "created_at": "2015-04-04T10:59:27.000Z",
    "username": "PoesiasLagrimas"
  },
  {
    "description": "Survivor of Terrorism. @ACTforAmerica Founder & Chairman. NYT Best-Selling Author. National Security Expert. RTs/Likes are NOT Endorsements. OFFICIAL ACCOUNT.",
    "name": "Brigitte Gabriel",
    "verified_type": "blue",
    "public_metrics": {
      "followers_count": 1385036,
      "following_count": 2430,
      "tweet_count": 53611,
      "listed_count": 3410,
      "like_count": 88553,
      "media_count": 5944
    },
    "id": "722528529716383744",
    "created_at": "2016-04-19T20:53:20.000Z",
    "username": "ACTBrigitte"
  },
  {
    "description": "xxx \u2022 Virginia \u2022 acab",
    "name": ".",
    "verified_type": "none",
    "public_metrics": {
      "followers_count": 166,
      "following_count": 277,
      "tweet_count": 4234,
      "listed_count": 0,
      "like_count": 10750,
      "media_count": 441
    },
    "id": "2324892690",
    "created_at": "2014-02-03T05:32:53.000Z",
    "username": "justxkyle"
  },
  {
    "description": "To stop the defamation of the Jewish people, and secure justice and fair treatment to all. @JGreenblattADL, @ADL_Tracker, @adlisrael #FightingHateForGood \ud83c\udf97\ufe0f",
    "name": "ADL",
    "verified_type": "business",
    "public_metrics": {
      "followers_count": 336197,
      "following_count": 3703,
      "tweet_count": 37970,
      "listed_count": 1722,
      "like_count": 9018,
      "media_count": 7636
    },
    "id": "19670226",
    "created_at": "2009-01-28T19:31:55.000Z",
    "username": "ADL"
  },
  {
    "description": "Greenpeace exists because this fragile Earth deserves a voice. It needs solutions. It needs change. It needs action.\n\nFind us on Bluesky, Mastodon, and Threads.",
    "name": "Greenpeace International",
    "verified_type": "business",
    "public_metrics": {
      "followers_count": 1771423,
      "following_count": 4106,
      "tweet_count": 91730,
      "listed_count": 17431,
      "like_count": 24805,
      "media_count": 24760
    },
    "id": "3459051",
    "created_at": "2007-04-04T20:30:34.000Z",
    "username": "Greenpeace"
  },
  {
    "description": "| Father | Social Media Strategist | Brand Development | R/T's Not Endorsements | BREAKING HEADLINES | #BillsMafia |",
    "name": "Chuck Callesto",
    "verified_type": "blue",
    "public_metrics": {
      "followers_count": 927007,
      "following_count": 10348,
      "tweet_count": 106889,
      "listed_count": 2603,
      "like_count": 19056,
      "media_count": 16856
    },
    "id": "4765364386",
    "created_at": "2016-01-10T15:12:40.000Z",
    "username": "ChuckCallesto"
  },
  {
    "description": "Official account of the United Nations. \nFor peace, dignity & equality on a healthy planet.",
    "name": "United Nations",
    "verified_type": "government",
    "public_metrics": {
      "followers_count": 16453831,
      "following_count": 1161,
      "tweet_count": 101050,
      "listed_count": 44722,
      "like_count": 1809,
      "media_count": 28806
    },
    "id": "14159148",
    "created_at": "2008-03-16T20:15:36.000Z",
    "username": "UN"
  },
  {
    "description": "\ud83d\udca1 Entrepreneur Magazine \ud83d\udcb0 Top Marketing Leader \n\u2764\ufe0f Founder \ud83d\udcc6 @Calendar & \ud83d\udcb2@Due \n\ud83d\udcc8 Nations #1 Connector",
    "name": "John Rampton",
    "verified_type": "blue",
    "public_metrics": {
      "followers_count": 1150526,
      "following_count": 529051,
      "tweet_count": 41816,
      "listed_count": 6091,
      "like_count": 18930,
      "media_count": 19246
    },
    "id": "76966092",
    "created_at": "2009-09-24T15:31:23.000Z",
    "username": "johnrampton"
  },
  {
    "description": "Host of \u201cTomi Lahren is Fearless\u201d @tlisfearless on @Outkick and @foxnews @foxnewsradio commentator",
    "name": "Tomi Lahren",
    "verified_type": "blue",
    "public_metrics": {
      "followers_count": 2865687,
      "following_count": 1448,
      "tweet_count": 39928,
      "listed_count": 6243,
      "like_count": 24479,
      "media_count": 4282
    },
    "id": "468646961",
    "created_at": "2012-01-19T19:19:11.000Z",
    "username": "TomiLahren"
  },
  {
    "description": "Operating at the center of an ecosystem working to improve outcomes and to create a world where healthcare has no limits.",
    "name": "GE HealthCare",
    "verified_type": "business",
    "public_metrics": {
      "followers_count": 113288,
      "following_count": 2848,
      "tweet_count": 27385,
      "listed_count": 2065,
      "like_count": 7434,
      "media_count": 7746
    },
    "id": "15383592",
    "created_at": "2008-07-10T21:33:25.000Z",
    "username": "GEHealthCare"
  },
  {
    "description": "Senior writer covering security, surveillance and privacy for @Forbes. Tip me anything sensitive on Signal: +1 929-512-7964. Email: tbrewster@forbes.com.",
    "name": "Thomas Brewster",
    "verified_type": "none",
    "public_metrics": {
      "followers_count": 26650,
      "following_count": 4914,
      "tweet_count": 24101,
      "listed_count": 1007,
      "like_count": 18051,
      "media_count": 631
    },
    "id": "139362186",
    "created_at": "2010-05-02T10:59:25.000Z",
    "username": "iblametom"
  },
  {
    "description": "Seminole County Sheriff's Office",
    "name": "Seminole County S.O.",
    "verified_type": "blue",
    "public_metrics": {
      "followers_count": 30652,
      "following_count": 753,
      "tweet_count": 4515,
      "listed_count": 350,
      "like_count": 1503,
      "media_count": 2645
    },
    "id": "69052130",
    "created_at": "2009-08-26T18:13:11.000Z",
    "username": "SeminoleSO"
  },
  {
    "description": "unofficial wakaba & koshiro photographer \u2022 i make calendars every year \u2022 inst @veritphoto, same on tumblr",
    "name": "verit",
    "verified_type": "none",
    "public_metrics": {
      "followers_count": 2182,
      "following_count": 240,
      "tweet_count": 58244,
      "listed_count": 45,
      "like_count": 94893,
      "media_count": 6674
    },
    "id": "65158069",
    "created_at": "2009-08-12T20:55:07.000Z",
    "username": "asverit"
  },
  {
    "description": "Seize the Day and explore the world #Travel #Photographer. Keeper of sheep. Keeping the rejoin dream alive. https://t.co/WbZ8rEa0Gv",
    "name": "\u21bb\u0105\u0567",
    "verified_type": "none",
    "public_metrics": {
      "followers_count": 1145,
      "following_count": 1550,
      "tweet_count": 18305,
      "listed_count": 3,
      "like_count": 34306,
      "media_count": 967
    },
    "id": "1257522666",
    "created_at": "2013-03-10T17:25:00.000Z",
    "username": "NatWorldPhoto"
  },
  {
    "description": "Discover something Fresh with our new Rotten Tomatoes app!",
    "name": "Rotten Tomatoes",
    "verified_type": "business",
    "public_metrics": {
      "followers_count": 2362686,
      "following_count": 1457,
      "tweet_count": 66527,
      "listed_count": 14223,
      "like_count": 7534,
      "media_count": 31647
    },
    "id": "20108560",
    "created_at": "2009-02-05T00:06:55.000Z",
    "username": "RottenTomatoes"
  },
  {
    "description": "Artist, Somm, average Joe.",
    "name": "Joe Iurato",
    "verified_type": "none",
    "public_metrics": {
      "followers_count": 718,
      "following_count": 183,
      "tweet_count": 919,
      "listed_count": 27,
      "like_count": 300,
      "media_count": 114
    },
    "id": "349504177",
    "created_at": "2011-08-06T06:04:09.000Z",
    "username": "joeiurato"
  },
  {
    "description": "Started as a TV show on social issues hosted by Aamir Khan. The team now runs Paani Foundation - to create a drought-free and prosperous rural Maharashtra.",
    "name": "Satyamev Jayate",
    "verified_type": "blue",
    "public_metrics": {
      "followers_count": 998658,
      "following_count": 106,
      "tweet_count": 6369,
      "listed_count": 535,
      "like_count": 518,
      "media_count": 1761
    },
    "id": "513067381",
    "created_at": "2012-03-03T11:20:26.000Z",
    "username": "satyamevjayate"
  },
  {
    "description": "Promo | Mixtape Slots & Hosting | Digital Marketing | Artwork | Consulting \ud83d\udcb0 kdough@trapsntrunks.com",
    "name": "Traps N Trunks",
    "verified_type": "blue",
    "public_metrics": {
      "followers_count": 41569,
      "following_count": 10824,
      "tweet_count": 116055,
      "listed_count": 172,
      "like_count": 25854,
      "media_count": 22634
    },
    "id": "19268183",
    "created_at": "2009-01-21T00:54:01.000Z",
    "username": "trapsntrunks"
  },
  {
    "description": "",
    "name": "Kraft Recipes",
    "verified_type": "none",
    "public_metrics": {
      "followers_count": 27,
      "following_count": 0,
      "tweet_count": 1,
      "listed_count": 0,
      "like_count": 0,
      "media_count": 0
    },
    "id": "1038151504270712832",
    "created_at": "2018-09-07T19:46:21.000Z",
    "username": "kraftrecipes"
  },
  {
    "description": "\ud83d\udc15 Human to a Collie.  \n\ud83c\udfc0 Basketball junkie. \n\ud83e\udd96 @raptors enthusiast since '95  #WeTheNorth\n\ud83c\udff4\udb40\udc67\udb40\udc62\udb40\udc73\udb40\udc63\udb40\udc74\udb40\udc7f",
    "name": "\ud83c\udd96\ufe0f \ud83c\udff4\udb40\udc67\udb40\udc62\udb40\udc73\udb40\udc63\udb40\udc74\udb40\udc7f",
    "verified_type": "none",
    "public_metrics": {
      "followers_count": 169,
      "following_count": 1206,
      "tweet_count": 5093,
      "listed_count": 6,
      "like_count": 17260,
      "media_count": 1344
    },
    "id": "344202842",
    "created_at": "2011-07-28T18:00:55.000Z",
    "username": "neil_gorman"
  },
  {
    "description": "Field Director Services.             SE region. Proud of all our associates and service providers who take care of our customers day in and day out.",
    "name": "Angel Aponte",
    "verified_type": "none",
    "public_metrics": {
      "followers_count": 2033,
      "following_count": 590,
      "tweet_count": 1833,
      "listed_count": 8,
      "like_count": 13217,
      "media_count": 435
    },
    "id": "1271089315",
    "created_at": "2013-03-16T00:51:38.000Z",
    "username": "SE_RSM_Aponte"
  },
  {
    "description": "Actor first,now sports..Opinions are just MINE. \ud83d\udfe6\ud83c\uddf7\ud83c\uddfc https://t.co/DpRdrJmUVg grumpy skunky \ud83d\ude0e",
    "name": "Matthew Laurance",
    "verified_type": "none",
    "public_metrics": {
      "followers_count": 2400,
      "following_count": 1323,
      "tweet_count": 143385,
      "listed_count": 31,
      "like_count": 191739,
      "media_count": 4639
    },
    "id": "1329191972",
    "created_at": "2013-04-05T13:13:47.000Z",
    "username": "realLauro5"
  },
  {
    "description": "Columnist, @NYTOpinion\nAuthor, \"Why We're Polarized\"\nHost of \"The Ezra Klein Show\" podcast",
    "name": "Ezra Klein",
    "verified_type": "blue",
    "public_metrics": {
      "followers_count": 2505361,
      "following_count": 1408,
      "tweet_count": 7742,
      "listed_count": 20682,
      "like_count": 3904,
      "media_count": 388
    },
    "id": "18622869",
    "created_at": "2009-01-05T04:02:29.000Z",
    "username": "ezraklein"
  },
  {
    "description": "KTLA Managing Dir of Content and Coverage  (past: KTTV, KCAL, WBZ, WCVB, WHDH, WBCN), BU grad, producer of: Morgan Freeman's \u201cDear Kobe\u201d and Vin Scully's \"Home\"",
    "name": "Pete Wilgoren",
    "verified_type": "none",
    "public_metrics": {
      "followers_count": 6090,
      "following_count": 6284,
      "tweet_count": 44870,
      "listed_count": 142,
      "like_count": 30063,
      "media_count": 3803
    },
    "id": "26619399",
    "created_at": "2009-03-25T23:04:43.000Z",
    "username": "WILGOREN"
  },
  {
    "description": "",
    "name": "Chris Christie",
    "verified_type": "blue",
    "public_metrics": {
      "followers_count": 109567,
      "following_count": 194,
      "tweet_count": 2805,
      "listed_count": 1607,
      "like_count": 178,
      "media_count": 1077
    },
    "id": "1347285918",
    "created_at": "2013-04-12T17:12:47.000Z",
    "username": "ChrisChristie"
  },
  {
    "description": "Unapologetic. Fearless.\nProgressive Politican. \n1st Female IND Councillor elected to Seanad Eireann.",
    "name": "Senator Sharon Keogan",
    "verified_type": "blue",
    "public_metrics": {
      "followers_count": 35028,
      "following_count": 1958,
      "tweet_count": 4607,
      "listed_count": 71,
      "like_count": 16881,
      "media_count": 943
    },
    "id": "2306617530",
    "created_at": "2014-01-23T13:57:38.000Z",
    "username": "SenatorKeogan"
  },
  {
    "description": "Appointed by Pres Trump as Ambassador to Israel 2025. Fmr AR Gov 1996-2007.  Bass Guitarist, \"Papa\" to 7 cutest grandkids in world! Author of 14 books.",
    "name": "Ambassador Mike Huckabee",
    "verified_type": "blue",
    "public_metrics": {
      "followers_count": 1988774,
      "following_count": 594,
      "tweet_count": 16035,
      "listed_count": 9397,
      "like_count": 271,
      "media_count": 2664
    },
    "id": "15416505",
    "created_at": "2008-07-13T17:09:21.000Z",
    "username": "GovMikeHuckabee"
  },
  {
    "description": "NADA",
    "name": "ALGUIEN",
    "verified_type": "none",
    "public_metrics": {
      "followers_count": 0,
      "following_count": 1,
      "tweet_count": 0,
      "listed_count": 0,
      "like_count": 10,
      "media_count": 0
    },
    "id": "1666222553508065280",
    "created_at": "2023-06-06T23:16:38.000Z",
    "username": "jimcarrey"
  },
  {
    "description": "ITV quizzer. For signed photos, Potato, ITV White City Place, 201 Wood Lane W12 7RU. For media enquiries, Celeb Agents, 0203 198 2200, sue@celebagents.co.uk.",
    "name": "Anne Hegerty",
    "verified_type": "none",
    "public_metrics": {
      "followers_count": 148805,
      "following_count": 791,
      "tweet_count": 23492,
      "listed_count": 112,
      "like_count": 32790,
      "media_count": 228
    },
    "id": "2787451110",
    "created_at": "2014-09-03T07:55:08.000Z",
    "username": "anne_hegerty"
  },
  {
    "description": "",
    "name": "Anwar",
    "verified_type": "none",
    "public_metrics": {
      "followers_count": 145,
      "following_count": 84,
      "tweet_count": 3845,
      "listed_count": 0,
      "like_count": 29914,
      "media_count": 118
    },
    "id": "966080485691707392",
    "created_at": "2018-02-20T22:41:51.000Z",
    "username": "AnwarMyanmar"
  },
  {
    "description": "Cottonian. I write for THE HINDU. Ex-Reuters,The Tribune, HT. Links not endorsements, views personal https://t.co/2W86rs1l0A",
    "name": "Vikas Vasudeva",
    "verified_type": "none",
    "public_metrics": {
      "followers_count": 1682,
      "following_count": 680,
      "tweet_count": 6260,
      "listed_count": 30,
      "like_count": 1028,
      "media_count": 215
    },
    "id": "168051289",
    "created_at": "2010-07-18T07:09:35.000Z",
    "username": "vasudevavikas"
  },
  {
    "description": "The USO is for the people who serve. Strengthening the well-being of the people serving in America\u2019s military and their families.",
    "name": "USO",
    "verified_type": "blue",
    "public_metrics": {
      "followers_count": 168548,
      "following_count": 930,
      "tweet_count": 23099,
      "listed_count": 1863,
      "like_count": 14119,
      "media_count": 8320
    },
    "id": "36681590",
    "created_at": "2009-04-30T14:59:09.000Z",
    "username": "The_USO"
  },
  {
    "description": "Historian of China & Central Asia and mandolinist w By & By. Work on Xinjiang, Qing, Silk Road, & stringed instruments across Eurasia.@jimmillward@bsky.social",
    "name": "James Millward \u7c73\u83ef\u5065",
    "verified_type": "none",
    "public_metrics": {
      "followers_count": 28395,
      "following_count": 920,
      "tweet_count": 8416,
      "listed_count": 476,
      "like_count": 2249,
      "media_count": 326
    },
    "id": "285003303",
    "created_at": "2011-04-20T10:54:46.000Z",
    "username": "JimMillward"
  },
  {
    "description": "Inveterate complainer, armchair activist, keyboard warrior, cartoonist, writer, columnist. Snr Editor for Inclusive Storytelling at The New Humanitarian.",
    "name": "gathara",
    "verified_type": "none",
    "public_metrics": {
      "followers_count": 197203,
      "following_count": 3113,
      "tweet_count": 216794,
      "listed_count": 491,
      "like_count": 291,
      "media_count": 7443
    },
    "id": "15659814",
    "created_at": "2008-07-30T13:13:41.000Z",
    "username": "gathara"
  },
  {
    "description": "https://t.co/QU9ID6rQFK\n\nSee you there.",
    "name": "Virginia Heffernan",
    "verified_type": "none",
    "public_metrics": {
      "followers_count": 119187,
      "following_count": 3874,
      "tweet_count": 58657,
      "listed_count": 2064,
      "like_count": 86065,
      "media_count": 2054
    },
    "id": "4282171",
    "created_at": "2007-04-12T02:18:44.000Z",
    "username": "page88"
  },
  {
    "description": "News Junkie | SAfm #TheTalkingPoint 9H00-12H00 daily|  MC/Moderator |",
    "name": "Cathy Mohlahlana",
    "verified_type": "none",
    "public_metrics": {
      "followers_count": 299642,
      "following_count": 1281,
      "tweet_count": 25279,
      "listed_count": 291,
      "like_count": 9310,
      "media_count": 651
    },
    "id": "236328898",
    "created_at": "2011-01-10T10:09:18.000Z",
    "username": "CathyMohlahlana"
  },
  {
    "description": "India\u2019s most watched Hindi News Channel. Follow for latest/breaking News Alerts from all over the Globe. FB: https://t.co/IJtJpoipue",
    "name": "India TV",
    "verified_type": "blue",
    "public_metrics": {
      "followers_count": 2533788,
      "following_count": 28,
      "tweet_count": 915223,
      "listed_count": 2211,
      "like_count": 36,
      "media_count": 282614
    },
    "id": "34245009",
    "created_at": "2009-04-22T11:26:34.000Z",
    "username": "indiatvnews"
  },
  {
    "description": "Kashmiri Pandit Channel News & Global updates . We report other side of the coin which goes unreported by Main stream Media. \ud83c\udf31\u262e\ufe0f\ud83d\uddfa\ud83d\udccdRefugee in Exile",
    "name": "Kashmiri Pandit News Channel",
    "verified_type": "none",
    "public_metrics": {
      "followers_count": 24101,
      "following_count": 614,
      "tweet_count": 12685,
      "listed_count": 56,
      "like_count": 6083,
      "media_count": 3022
    },
    "id": "722735254839156736",
    "created_at": "2016-04-20T10:34:47.000Z",
    "username": "kpnewschannel"
  },
  {
    "description": "Prisoner in a Free land",
    "name": "Azizullah Bugti",
    "verified_type": "none",
    "public_metrics": {
      "followers_count": 31988,
      "following_count": 9212,
      "tweet_count": 11701,
      "listed_count": 47,
      "like_count": 7125,
      "media_count": 1699
    },
    "id": "320740749",
    "created_at": "2011-06-20T13:02:31.000Z",
    "username": "AzizullahBugti"
  },
  {
    "description": "Artist, Professor at LIU/Post, Collector, Advisor. Ceramics and Paintings. #worksofolt @frankolt",
    "name": "Frank Olt",
    "verified_type": "none",
    "public_metrics": {
      "followers_count": 4169,
      "following_count": 4112,
      "tweet_count": 11520,
      "listed_count": 125,
      "like_count": 2042,
      "media_count": 146
    },
    "id": "20553176",
    "created_at": "2009-02-10T22:32:44.000Z",
    "username": "frankolt"
  },
  {
    "description": "\u2018NIGHTMARES OF THE WEST\u2019 AVAILABLE NOW ON @purenoiserecs",
    "name": "Strike Anywhere",
    "verified_type": "none",
    "public_metrics": {
      "followers_count": 9971,
      "following_count": 9308,
      "tweet_count": 893,
      "listed_count": 208,
      "like_count": 29,
      "media_count": 40
    },
    "id": "76105335",
    "created_at": "2009-09-21T18:44:22.000Z",
    "username": "_StrikeAnywhere"
  },
  {
    "description": "Music, Finance, Decentralization, fan of satire. Random observations about life and the universe. Question authority no matter who's in charge",
    "name": "Ed Maguire",
    "verified_type": "blue",
    "public_metrics": {
      "followers_count": 2500,
      "following_count": 5048,
      "tweet_count": 22020,
      "listed_count": 49,
      "like_count": 97123,
      "media_count": 576
    },
    "id": "19504125",
    "created_at": "2009-01-25T20:47:18.000Z",
    "username": "eemaguire"
  },
  {
    "description": "\ud83d\udc9a: @chrispaulfamfdn \ud83c\udfa5: @ohhdip",
    "name": "Chris Paul",
    "verified_type": "blue",
    "public_metrics": {
      "followers_count": 8165214,
      "following_count": 907,
      "tweet_count": 6672,
      "listed_count": 14186,
      "like_count": 2014,
      "media_count": 1235
    },
    "id": "53853197",
    "created_at": "2009-07-05T06:25:22.000Z",
    "username": "CP3"
  },
  {
    "description": "I can be better.",
    "name": "abbie maley",
    "verified_type": "none",
    "public_metrics": {
      "followers_count": 160821,
      "following_count": 404,
      "tweet_count": 4436,
      "listed_count": 329,
      "like_count": 11117,
      "media_count": 909
    },
    "id": "91845425",
    "created_at": "2009-11-22T18:56:25.000Z",
    "username": "abbiemaley"
  },
  {
    "description": "Author. Columnist. Screenwriter. Motivational Speaker. Youtuber.",
    "name": "Chetan Bhagat",
    "verified_type": "blue",
    "public_metrics": {
      "followers_count": 12045932,
      "following_count": 175,
      "tweet_count": 17298,
      "listed_count": 6933,
      "like_count": 5129,
      "media_count": 1512
    },
    "id": "44588485",
    "created_at": "2009-06-04T10:30:19.000Z",
    "username": "chetan_bhagat"
  },
  {
    "description": "AGU is a global community supporting more than half a million advocates and professionals in Earth and space sciences.",
    "name": "AGU (American Geophysical Union)",
    "verified_type": "business",
    "public_metrics": {
      "followers_count": 82528,
      "following_count": 3435,
      "tweet_count": 92368,
      "listed_count": 1861,
      "like_count": 8766,
      "media_count": 22632
    },
    "id": "39530187",
    "created_at": "2009-05-12T16:05:05.000Z",
    "username": "theAGU"
  },
  {
    "description": "Rheumatology Team| Kristy Moore NP, Christy Schulte NP, Maria Sullivan, PA Satire",
    "name": "ArthritisCenterSTL",
    "verified_type": "blue",
    "public_metrics": {
      "followers_count": 1044,
      "following_count": 640,
      "tweet_count": 8239,
      "listed_count": 3,
      "like_count": 31633,
      "media_count": 1152
    },
    "id": "1219842329521029120",
    "created_at": "2020-01-22T04:41:00.000Z",
    "username": "ArthritisSTL"
  },
  {
    "description": "\"Watson is a brilliant polemicist.\" The Spectator.....\u201dPopular cutting edge political commentator.\u201d The Jewish Voice https://t.co/rZCVlVSOYm",
    "name": "Paul Joseph Watson",
    "verified_type": "blue",
    "public_metrics": {
      "followers_count": 1401695,
      "following_count": 1046,
      "tweet_count": 93839,
      "listed_count": 7763,
      "like_count": 11957,
      "media_count": 16922
    },
    "id": "18643437",
    "created_at": "2009-01-05T20:04:23.000Z",
    "username": "PrisonPlanet"
  }
]